{"logFileForTest/forTest.log": {"Digital_Contact@ADRqihXcPKl[1]": 8.0, "Digital_Contact@ADReOcxEwDd[1]": 16.0, "Digital_Contact@ADRcTbbBLpC[1]": 12.0, "Digital_Contact@ADRLyMQBQea[1]": 52.0, "Digital_Contact@ADREnsKCrwf[1]": 44.0, "Digital_Contact@ADRDJnsbOtT[1]": 20.0, "Digital_Contact@ADRBzxgJWIg[1]": 20.0, "Digital_Contact@ADROLytggsa[1]": 52.0, "Digital_Contact@ADROKHQrjBv[1]": 16.0, "Digital_Contact@ADRbvTfDXye[1]": 16.0, "Digital_Contact@ADRasQXPVfy[1]": 12.0, "Digital_Contact@ADRMPMzRZil[1]": 76.0, "Digital_Contact@ADRIXdalpKf[1]": 24.0, "Digital_Contact@ADRDBpYRoXW[1]": 40.0, "Digital_Contact@ADRETupGSZi[1]": 24.0, "Digital_Contact@ADRznvIGTwW[1]": 72.0, "Digital_Contact@ADRQNSMXYuA[1]": 24.0, "Digital_Contact@ADRcqtBLwsW[1]": 20.0, "Digital_Contact@ADRcCWEgwpU[1]": 12.0, "Digital_Contact@ADRSeEucqcG[1]": 48.0, "Digital_Contact@ADRonpNVTkX[1]": 32.0, "Digital_Contact@ADRblcVKnoq[1]": 12.0, "Digital_Contact@ADRgsEuawxz[1]": 16.0, "Digital_Contact@ADRQXGFWunY[1]": 56.0, "Digital_Contact@ADRkRJfYHEo[1]": 20.0, "Digital_Contact@ADRQnkEdUmd[1]": 20.0, "Digital_Contact@ADRRpQoOlUb[1]": 44.0, "Digital_Contact@ADRbHrBSZsv[1]": 56.0, "Digital_Contact@ADRYWbglVyi[1]": 12.0, "Digital_Contact@ADRtGkRetrI[1]": 20.0, "Digital_Contact@ADRnpEhBirq[1]": 20.0, "Digital_Contact@ADRDTEKifpL[1]": 64.0, "Digital_Contact@ADRaPRONKBZ[1]": 32.0, "Digital_Contact@ADRPHsBxctt[1]": 20.0, "Digital_Contact@ADRchSAkFwf[1]": 44.0, "Digital_Contact@ADRpgdaHXGC[1]": 56.0, "Digital_Contact@ADRffBaaUxa[1]": 32.0, "Digital_Contact@ADRbChaxxrR[1]": 32.0, "Digital_Contact@ADRRFisCpiI[1]": 12.0, "Digital_Contact@ADRfsyncmEU[1]": 56.0, "Digital_Contact@ADRBbsIOQWj[1]": 12.0, "Digital_Contact@ADRxQxSuZfu[1]": 12.0, "Digital_Contact@ADRyLewKcZF[1]": 12.0, "Digital_Contact@ADRjJPSndwv[1]": 52.0, "Digital_Contact@ADRxPcHjHwa[1]": 20.0, "Digital_Contact@ADRQriWbgIu[1]": 20.0, "Digital_Contact@ADRClQUFfYo[1]": 28.0, "Digital_Contact@ADRtAKgAmzh[1]": 48.0, "Digital_Contact@ADRItEVJZnw[1]": 20.0, "Digital_Contact@ADRXOIUiiKR[1]": 20.0, "Digital_Contact@ADRulwkvvMv[1]": 20.0, "Digital_Contact@ADRPySPIUja[1]": 48.0, "Digital_Contact@ADReNryJSkc[1]": 12.0, "Digital_Contact@ADRYMbqNmYs[1]": 16.0, "Digital_Contact@ADRGPYZyqXk[1]": 16.0, "Digital_Contact@ADRBfFfClfm[1]": 64.0, "Digital_Contact@ADRWgKimCUb[1]": 20.0, "Digital_Contact@ADRWOUOJjte[1]": 12.0, "Digital_Contact@ADRdSCcNVVF[1]": 20.0, "Digital_Contact@ADRlimxDWCL[1]": 68.0, "Digital_Contact@ADRLJLFVrkh[1]": 24.0, "Digital_Contact@ADRRPcPiGPl[1]": 16.0, "Digital_Contact@ADReAckXJgi[1]": 20.0, "Digital_Contact@ADRbxVzwxdV[1]": 68.0, "Digital_Contact@ADRiaRKqPyp[1]": 20.0, "Digital_Contact@ADRMjjELWJc[1]": 8.0, "Digital_Contact@ADRjYerxZYB[1]": 20.0, "Digital_Contact@ADRftlbtyGa[1]": 72.0, "Digital_Contact@ADRPDLnUIKb[1]": 16.0, "Digital_Contact@ADRahNLUSAR[1]": 8.0, "Digital_Contact@ADRZChKQEFX[1]": 20.0, "Digital_Contact@ADRAswISxIq[1]": 48.0, "Digital_Contact@ADRHzSbKkxk[1]": 24.0, "Digital_Contact@ADReRGUJXkm[1]": 16.0, "Digital_Contact@ADRYYCLLYxk[1]": 16.0, "Digital_Contact@ADRMIyEaSLu[1]": 68.0, "Digital_Contact@ADRyrbYNsXX[1]": 4.0, "Digital_Contact@ADRBDATOzts[1]": 24.0, "Digital_Contact@ADRwyJUpuOJ[1]": 28.0, "Digital_Contact@ADRbFrnTTph[1]": 64.0, "Digital_Contact@ADRzNcfhbOd[1]": 8.0, "Digital_Contact@ADRjbQZtNrz[1]": 12.0, "Digital_Contact@ADRPamKMVuJ[1]": 16.0, "Digital_Contact@ADRcgWcXxfx[1]": 52.0, "Digital_Contact@ADRBtIdXtKe[1]": 24.0, "Digital_Contact@ADRbcmcxERh[1]": 16.0, "Digital_Contact@ADRPSArFtdV[1]": 24.0, "Digital_Contact@ADRJcpnaFck[1]": 60.0, "Digital_Contact@ADRkZhEqLPk[1]": 16.0, "Digital_Contact@ADRQGlynfsa[1]": 16.0, "Digital_Contact@ADRToNGGJlJ[1]": 32.0, "Digital_Contact@ADRnesdjmDu[1]": 76.0, "Digital_Contact@ADRXJceWszG[1]": 20.0, "Digital_Contact@ADRDkPkdrub[1]": 28.0, "Digital_Contact@ADRIzEBwLQu[1]": 12.0, "Digital_Contact@ADREEMoLGyF[1]": 68.0, "Digital_Contact@ADRIShcFKVn[1]": 32.0, "Digital_Contact@ADRZFpeyHyA[1]": 12.0, "Digital_Contact@ADRFqegdYSi[1]": 16.0, "Digital_Contact@ADRZKgzkINy[1]": 48.0, "Digital_Contact@ADRkURQYBCE[1]": 16.0, "Digital_Contact@ADRSwTsSImb[1]": 8.0, "Digital_Contact@ADRtYXAdcwK[1]": 20.0, "Digital_Contact@ADRNeuORRiZ[1]": 64.0, "Digital_Contact@ADRyccQDYeA[1]": 20.0, "Digital_Contact@ADRuQPxaVxd[1]": 12.0, "Digital_Contact@ADRSnfDILhx[1]": 12.0, "Digital_Contact@ADRdJhdZOtG[1]": 72.0, "Digital_Contact@ADRkDYbdwPG[1]": 28.0, "Digital_Contact@ADRjZbmEapa[1]": 32.0, "Digital_Contact@ADRmEvUBxtk[1]": 32.0, "Digital_Contact@ADRuEjgkBDb[1]": 68.0, "Digital_Contact@ADRVUxWYchX[1]": 8.0, "Digital_Contact@ADRiwvUvmSm[1]": 20.0, "Digital_Contact@ADRgBlStgzw[1]": 24.0, "Digital_Contact@ADRJCICcDUg[1]": 48.0, "Digital_Contact@ADRyZuAujLm[1]": 12.0, "Digital_Contact@ADRrvJkENpP[1]": 16.0, "Digital_Contact@ADRIjbvrOox[1]": 16.0, "Digital_Contact@ADRNaHcapAk[1]": 52.0, "Digital_Contact@ADRjUZvOyaz[1]": 28.0, "Digital_Contact@ADRQgsSDjpi[1]": 8.0, "Digital_Contact@ADRgrpdNuxd[1]": 16.0, "Digital_Contact@ADRubVequJR[1]": 64.0, "Digital_Contact@ADRkPtRtBUz[1]": 20.0, "Digital_Contact@ADRIuuyNDhU[1]": 20.0, "Digital_Contact@ADRNjKdqCrP[1]": 36.0, "Digital_Contact@ADRfVhqRskz[1]": 76.0, "Digital_Contact@ADRMvycKhSw[1]": 4.0, "Digital_Contact@ADRnYyxZMEc[1]": 28.0, "Digital_Contact@ADRgPKooTCM[1]": 72.0, "Digital_Contact@ADRKWKJOffR[1]": 20.0, "Digital_Contact@ADReEPKaKFc[1]": 32.0, "Digital_Contact@ADRRvlJsFoZ[1]": 16.0, "Digital_Contact@ADRaFaYpHio[1]": 48.0, "Digital_Contact@ADRwqqXTrLu[1]": 32.0, "Digital_Contact@ADReDGJGdrP[1]": 28.0, "Digital_Contact@ADRTdWVXwpY[1]": 16.0, "Digital_Contact@ADRSpnGNIvM[1]": 32.0, "Digital_Contact@ADRtYQhyyAI[1]": 36.0, "Digital_Contact@ADRoVXOxPAz[1]": 12.0, "Digital_Contact@ADRhfKAkuMP[1]": 20.0, "Digital_Contact@ADRjDksgjpn[1]": 52.0, "Digital_Contact@ADRfBTfdRKR[1]": 12.0, "Digital_Contact@ADRTFOmoXmk[1]": 16.0, "Digital_Contact@ADRKraXMKqG[1]": 20.0, "Digital_Contact@ADRReXlIoAi[1]": 44.0, "Digital_Contact@ADRNIMWiVGX[1]": 20.0, "Digital_Contact@ADRBZlcbyKF[1]": 20.0, "Digital_Contact@ADRpLIirsdp[1]": 16.0, "Digital_Contact@ADRMfWngacp[1]": 68.0, "Digital_Contact@ADREeaNJgGm[1]": 16.0, "Digital_Contact@ADRzIZkeAnX[1]": 24.0, "Digital_Contact@ADRYLFmEzAu[1]": 12.0, "Digital_Contact@ADRyvCEOnyV[1]": 68.0, "Digital_Contact@ADREjpSWcFF[1]": 24.0, "Digital_Contact@ADRJrtZlrCX[1]": 12.0, "Digital_Contact@ADRrzKnXTgY[1]": 32.0, "Digital_Contact@ADRWyWEMynf[1]": 60.0, "Digital_Contact@ADRYmfBTOMn[1]": 24.0, "Digital_Contact@ADRLpckBQYn[1]": 36.0, "Digital_Contact@ADRqWFnqilH[1]": 8.0, "Digital_Contact@ADRJatGYWKH[1]": 56.0, "Digital_Contact@ADRkYMxDLNp[1]": 32.0, "Digital_Contact@ADRVqlKkXjS[1]": 28.0, "Digital_Contact@ADRBQedGSbI[1]": 8.0, "Digital_Contact@ADRdTgvhkAf[1]": 52.0, "Digital_Contact@ADRIGhTgLsh[1]": 20.0, "Digital_Contact@ADRjgXPFdRR[1]": 12.0, "Digital_Contact@ADRMGvMNTTA[1]": 16.0, "Digital_Contact@ADRMNjZCyBz[1]": 60.0, "Digital_Contact@ADRkNgjnbGk[1]": 12.0, "Digital_Contact@ADRUZfRHAwW[1]": 28.0, "Digital_Contact@ADRVEbbENOf[1]": 20.0, "Digital_Contact@ADRGJzqrlSw[1]": 40.0, "Digital_Contact@ADRezyDnuwQ[1]": 32.0, "Digital_Contact@ADRraPfjCte[1]": 20.0, "Digital_Contact@ADRFAIllsyg[1]": 16.0, "Digital_Contact@ADRyYFKkUyG[1]": 72.0, "Digital_Contact@ADRtCStbFWB[1]": 12.0, "Digital_Contact@ADRlnEkXoPj[1]": 24.0, "Digital_Contact@ADRdkGuyLrN[1]": 28.0, "Digital_Contact@ADRlGqiMHhb[1]": 60.0, "Digital_Contact@ADRbeCsrfvY[1]": 4.0, "Digital_Contact@ADRHYMXOTGp[1]": 32.0, "Digital_Contact@ADRVaArPhhT[1]": 12.0, "Digital_Contact@ADRAtHjerhp[1]": 44.0, "Digital_Contact@ADRDZdZPlAI[1]": 8.0, "Digital_Contact@ADREzHsFiJI[1]": 16.0, "Digital_Contact@ADRGpGYjvYB[1]": 44.0, "Digital_Contact@ADRoDZdHbcF[1]": 64.0, "Digital_Contact@ADRAsDiDWeu[1]": 24.0, "Digital_Contact@ADRuYrdQtTw[1]": 40.0, "Digital_Contact@ADRJRoxzuvU[1]": 28.0, "Digital_Contact@ADRnPjTcfqi[1]": 56.0, "Digital_Contact@ADRIYsxeWtN[1]": 32.0, "Digital_Contact@ADRVNQKBPZg[1]": 8.0, "Digital_Contact@ADRtisIsPJk[1]": 16.0, "Digital_Contact@ADReeYZljZl[1]": 68.0, "Digital_Contact@ADRbUjXwxJb[1]": 20.0, "Digital_Contact@ADRPZGMsYOT[1]": 16.0, "Digital_Contact@ADRUhBgLIlp[1]": 24.0, "Digital_Contact@ADRWEixfYie[1]": 56.0, "Digital_Contact@ADRKEIQBAor[1]": 16.0, "Digital_Contact@ADRtCeAcBMH[1]": 16.0, "Digital_Contact@ADRmZrmitZn[1]": 20.0, "Digital_Contact@ADRPagdjBrt[1]": 44.0, "Digital_Contact@ADRDNsxhkuM[1]": 12.0, "Digital_Contact@ADRbQLxaUDc[1]": 20.0, "Digital_Contact@ADRZKcrOaPi[1]": 32.0, "Digital_Contact@ADRYqHYODCd[1]": 60.0, "Digital_Contact@ADRRWWRjZIn[1]": 4.0, "Digital_Contact@ADRvYfWwnGN[1]": 12.0, "Digital_Contact@ADRXOoWTbQT[1]": 24.0, "Digital_Contact@ADRFGhxgGMI[1]": 52.0, "Digital_Contact@ADRKmAHZUxu[1]": 12.0, "Digital_Contact@ADRZstiGisK[1]": 28.0, "Digital_Contact@ADRWBYBnbCq[1]": 28.0, "Digital_Contact@ADRooHMKiZi[1]": 68.0, "Digital_Contact@ADRaeJzlQrZ[1]": 16.0, "Digital_Contact@ADRnPViyVkA[1]": 16.0, "Digital_Contact@ADRVPsyFFOc[1]": 24.0, "Digital_Contact@ADRdmzEfHma[1]": 60.0, "Digital_Contact@ADRrhfeMgrI[1]": 24.0, "Digital_Contact@ADRKnyXztMu[1]": 36.0, "Digital_Contact@ADRHrcqwzgn[1]": 12.0, "Digital_Contact@ADRDyRFfYOu[1]": 56.0, "Digital_Contact@ADRDqKluCqD[1]": 16.0, "Digital_Contact@ADRkxOdjfav[1]": 20.0, "Digital_Contact@ADRqCTDqUzB[1]": 16.0, "Digital_Contact@ADRSskTQInv[1]": 48.0, "Digital_Contact@ADRFfUzyJHs[1]": 32.0, "Digital_Contact@ADRztREHloK[1]": 24.0, "Digital_Contact@ADRSszwHSTk[1]": 12.0, "Digital_Contact@ADRoTdtRTii[1]": 60.0, "Digital_Contact@ADRPxqbEQFN[1]": 28.0, "Digital_Contact@ADReyIpYipl[1]": 28.0, "Digital_Contact@ADRffjQifXi[1]": 12.0, "Digital_Contact@ADRHeMJqarn[1]": 76.0, "Digital_Contact@ADRDRueCXAz[1]": 12.0, "Digital_Contact@ADRkRyCUFOa[1]": 28.0, "Digital_Contact@ADRkJICkNWL[1]": 12.0, "Digital_Contact@ADRCnTSoRqB[1]": 44.0, "Digital_Contact@ADRvqxrMIpb[1]": 28.0, "Digital_Contact@ADRlgwJvLmO[1]": 12.0, "Digital_Contact@ADRociFfAVD[1]": 32.0, "Digital_Contact@ADRuogCUaCf[1]": 52.0, "Digital_Contact@ADRanRTrmlD[1]": 32.0, "Digital_Contact@ADRqudPgxMw[1]": 16.0, "Digital_Contact@ADRYFymiaXA[1]": 72.0, "Digital_Contact@ADRBbuXZsKH[1]": 20.0, "Digital_Contact@ADRWpSAtyru[1]": 16.0, "Digital_Contact@ADRpuBwFYqx[1]": 32.0, "Digital_Contact@ADRuayhfRrj[1]": 72.0, "Digital_Contact@ADRWsBnUGOB[1]": 20.0, "Digital_Contact@ADRXNymdPZw[1]": 8.0, "Digital_Contact@ADRgfmViHld[1]": 32.0, "Digital_Contact@ADRoyKGjUzV[1]": 80.0, "Digital_Contact@ADRJliHpCHd[1]": 48.0, "Digital_Contact@ADRZGUdeWwV[1]": 20.0, "Digital_Contact@ADRaXHcAipZ[1]": 12.0, "Digital_Contact@ADRWFashNwJ[1]": 60.0, "Digital_Contact@ADRClRHBwLp[1]": 28.0, "Digital_Contact@ADRTTNvnFaf[1]": 36.0, "Digital_Contact@ADRQqiznTEt[1]": 24.0, "Digital_Contact@ADRDnRhmkyZ[1]": 60.0, "Digital_Contact@ADRAmMtzTUZ[1]": 16.0, "Digital_Contact@ADRKbFAWcph[1]": 12.0, "Digital_Contact@ADRtRbPSHfB[1]": 4.0, "Digital_Contact@ADREBSDwdkQ[1]": 72.0, "Digital_Contact@ADRhldCsPfF[1]": 24.0, "Digital_Contact@ADRrqmMCdxz[1]": 16.0, "Digital_Contact@ADRqZTNxCWh[1]": 24.0, "Digital_Contact@ADRPSpxptbB[1]": 64.0, "Digital_Contact@ADRPPsgeveU[1]": 24.0, "Digital_Contact@ADRfYxSyHJA[1]": 20.0, "Digital_Contact@ADRXJxcYJWm[1]": 8.0, "Digital_Contact@ADRJBIxzHGD[1]": 64.0, "Digital_Contact@ADRMrKSrdlK[1]": 24.0, "Digital_Contact@ADRDsAiCbnZ[1]": 40.0, "Digital_Contact@ADRewgAviBM[1]": 24.0, "Digital_Contact@ADRpGKHExGs[1]": 48.0, "Digital_Contact@ADRHmjNmmOp[1]": 16.0, "Digital_Contact@ADRUHrjHWDk[1]": 20.0, "Digital_Contact@ADRFeAHCWHD[1]": 32.0, "Digital_Contact@ADROMnTOlMp[1]": 60.0, "Digital_Contact@ADROuLVyCFX[1]": 8.0, "Digital_Contact@ADRqZoqnfVI[1]": 12.0, "Digital_Contact@ADRcDyVceXa[1]": 8.0, "Digital_Contact@ADRFFUppBuB[1]": 44.0, "Digital_Contact@ADRJNtAxYDr[1]": 28.0, "Digital_Contact@ADRjtKwHuMw[1]": 36.0, "Digital_Contact@ADRSMkxxaRV[1]": 24.0, "Digital_Contact@ADRMqeGFYvS[1]": 68.0, "Digital_Contact@ADRKtBLvnMK[1]": 32.0, "Digital_Contact@ADRxsiGKosY[1]": 12.0, "Digital_Contact@ADRmKVblmLm[1]": 20.0, "Digital_Contact@ADRQkxJRbxu[1]": 44.0, "Digital_Contact@ADRotFGPjql[1]": 20.0, "Digital_Contact@ADRysgAUzCU[1]": 20.0, "Digital_Contact@ADRyBmsGvUu[1]": 20.0, "Digital_Contact@ADRKgjYpDiU[1]": 68.0, "Digital_Contact@ADRgGbjvoLv[1]": 20.0, "Digital_Contact@ADRdMVdAscB[1]": 8.0, "Digital_Contact@ADRIrWmlacd[1]": 20.0, "Digital_Contact@ADRezmFjAiq[1]": 64.0, "Digital_Contact@ADRaUmlgaZL[1]": 24.0, "Digital_Contact@ADRqiXzHSYB[1]": 12.0, "Digital_Contact@ADRuVLzOXKh[1]": 12.0, "Digital_Contact@ADRYPVkDvSI[1]": 64.0, "Digital_Contact@ADRDSBltQZJ[1]": 20.0, "Digital_Contact@ADRqwDltfxJ[1]": 16.0, "Digital_Contact@ADRcpOllyyx[1]": 24.0, "Digital_Contact@ADRMgiEToQc[1]": 52.0, "Digital_Contact@ADRXtlFcBWk[1]": 16.0, "Digital_Contact@ADRHPIiMAll[1]": 8.0, "Digital_Contact@ADRBbvPENOi[1]": 16.0, "Digital_Contact@ADRwOvOARSt[1]": 76.0, "Digital_Contact@ADRPVyAeGJQ[1]": 24.0, "Digital_Contact@ADRuXxCVDPM[1]": 20.0, "Digital_Contact@ADRxfesWehG[1]": 28.0, "Digital_Contact@ADRvGxxQsvf[1]": 68.0, "Digital_Contact@ADRagtvBtbM[1]": 20.0, "Digital_Contact@ADRVBeRRJgD[1]": 12.0, "Digital_Contact@ADRBMpNerQr[1]": 16.0, "Digital_Contact@ADRHSjevtpc[1]": 56.0, "Digital_Contact@ADRUDaSPUIY[1]": 8.0, "Digital_Contact@ADRGnWblxnO[1]": 24.0, "Digital_Contact@ADRmXzuvvWc[1]": 24.0, "Digital_Contact@ADRPaKbqdyE[1]": 64.0, "Digital_Contact@ADRIGVGTvHH[1]": 32.0, "Digital_Contact@ADRGoWmQyZQ[1]": 24.0, "Digital_Contact@ADRJZVpfpcG[1]": 16.0, "Digital_Contact@ADRRdIlGzps[1]": 60.0, "Digital_Contact@ADRARVhLeSO[1]": 24.0, "Digital_Contact@ADRdauBVYDT[1]": 16.0, "Digital_Contact@ADRLXpfOFKS[1]": 20.0, "Digital_Contact@ADRlAZUwqDn[1]": 60.0, "Digital_Contact@ADRgvPrMLGA[1]": 16.0, "Digital_Contact@ADRiFYnnWAt[1]": 24.0, "Digital_Contact@ADRhSagyzRM[1]": 16.0, "Digital_Contact@ADRyVsEddHT[1]": 72.0, "Digital_Contact@ADRhsAbLFAx[1]": 8.0, "Digital_Contact@ADRZpfmhBNa[1]": 20.0, "Digital_Contact@ADReDibDvnR[1]": 16.0, "Digital_Contact@ADRXHbHsNKa[1]": 68.0, "Digital_Contact@ADRalPmdUfL[1]": 4.0, "Digital_Contact@ADROFEVaenj[1]": 16.0, "Digital_Contact@ADRqcyVdUPJ[1]": 32.0, "Digital_Contact@ADRXlOjBjjA[1]": 64.0, "Digital_Contact@ADRgzezBWAt[1]": 20.0, "Digital_Contact@ADRqCTPBaDR[1]": 12.0, "Digital_Contact@ADRByceDoYv[1]": 16.0, "Digital_Contact@ADRuPtrtODN[1]": 68.0, "Digital_Contact@ADRHxtGsvsY[1]": 20.0, "Digital_Contact@ADRMdXnMuDX[1]": 20.0, "Digital_Contact@ADRkNSfjVaV[1]": 32.0}}